BloodHound_MCP.py
iflow_mcp_bloodhound_mcp_ai-1.0.0.dist-info/METADATA
iflow_mcp_bloodhound_mcp_ai-1.0.0.dist-info/WHEEL
iflow_mcp_bloodhound_mcp_ai-1.0.0.dist-info/entry_points.txt
iflow_mcp_bloodhound_mcp_ai-1.0.0.dist-info/top_level.txt
iflow_mcp_bloodhound_mcp_ai-1.0.0.dist-info/RECORD
