Metadata-Version: 2.4
Name: iflow-mcp_BloodHound-MCP-AI
Version: 1.0.0
Summary: BloodHound MCP Server for Active Directory security analysis
Author-email: MorDavid <mordavid@example.com>
License: MIT
Requires-Python: >=3.8
Requires-Dist: neo4j
Requires-Dist: python-dotenv
Requires-Dist: mcp-server>=0.1.0
Requires-Dist: fastmcp
